{
  "routes": [
    {
      "method": "GET",
      "path": "/clicks",
      "handler": "clicks.find",
      "config": {
        "policies": []
      }
    },
    {
      "method": "GET",
      "path": "/clicks/count",
      "handler": "clicks.count",
      "config": {
        "policies": []
      }
    },
    {
      "method": "GET",
      "path": "/clicks/:id",
      "handler": "clicks.findOne",
      "config": {
        "policies": []
      }
    },
    {
      "method": "POST",
      "path": "/clicks",
      "handler": "clicks.create",
      "config": {
        "policies": []
      }
    },
    {
      "method": "PUT",
      "path": "/clicks/:id",
      "handler": "clicks.update",
      "config": {
        "policies": []
      }
    },
    {
      "method": "DELETE",
      "path": "/clicks/:id",
      "handler": "clicks.delete",
      "config": {
        "policies": []
      }
    }
  ]
}
